odoo10_addon_base_onchange_rule-10.0.1.0.0.99.dev17-nspkg.pth
odoo/addons/base_onchange_rule/README.rst
odoo/addons/base_onchange_rule/__init__.py
odoo/addons/base_onchange_rule/__manifest__.py
odoo/addons/base_onchange_rule/hooks.py
odoo/addons/base_onchange_rule/demo/partner_demo.xml
odoo/addons/base_onchange_rule/i18n/base_onchange_rule.pot
odoo/addons/base_onchange_rule/models/__init__.py
odoo/addons/base_onchange_rule/models/ir_model.py
odoo/addons/base_onchange_rule/models/onchange_rule.py
odoo/addons/base_onchange_rule/models/onchange_rule_line.py
odoo/addons/base_onchange_rule/security/ir.model.access.csv
odoo/addons/base_onchange_rule/static/description/icon.png
odoo/addons/base_onchange_rule/views/onchange_rule_view.xml
odoo10_addon_base_onchange_rule-10.0.1.0.0.99.dev17.dist-info/METADATA
odoo10_addon_base_onchange_rule-10.0.1.0.0.99.dev17.dist-info/WHEEL
odoo10_addon_base_onchange_rule-10.0.1.0.0.99.dev17.dist-info/namespace_packages.txt
odoo10_addon_base_onchange_rule-10.0.1.0.0.99.dev17.dist-info/top_level.txt
odoo10_addon_base_onchange_rule-10.0.1.0.0.99.dev17.dist-info/RECORD
